<?xml version="1.0" encoding="UTF-8"?>
<!--
  Copyright (c) 2005 - 2006

  Licensed under the Apache License, Version 2.0 (the "License");
  you may not use this file except in compliance with the License.
  You may obtain a copy of the License at

      http://www.apache.org/licenses/LICENSE-2.0

  Unless required by applicable law or agreed to in writing, software
  distributed under the License is distributed on an "AS IS" BASIS,
  WITHOUT WARRANTIES OR CONDITIONS OF ANY KIND, either express or implied.
  See the License for the specific language governing permissions and
  limitations under the License.
-->

<!--
Forrest site.xml

This file contains an outline of the site's information content.  It is used to:
- Generate the website menus (though these can be overridden - see docs)
- Provide semantic, location-independent aliases for internal 'site:' URIs, eg
<link href="site:changes"> links to changes.html (or ../changes.html if in
  subdir).
- Provide aliases for external URLs in the external-refs section.  Eg, <link
  href="ext:cocoon"> links to http://cocoon.apache.org/

See http://forrest.apache.org/docs/linking.html for more info
-->

<site label="Eclim" href="" url="http://eclim.sourceforge.net/"
  xmlns="http://apache.org/forrest/linkmap/1.0" tab="home">

   <!-- Note: No matter what you configure here, Forrest will always try to load
       index.html when you request http://yourHost/.
       'How can I use a start-up-page other than index.html?' in the FAQs has more
       information tells you how to change that.
   -->
  <about label="About" tab="home">
    <index label="Index / News" href="index.html" description="Welcome to Eclim"/>
    <features label="Features" href="features.html" description="Features"/>
    <screenshots label="Screenshots" description="Eclim Screenshots"
        href="ext:screenshots"/>
    <download label="Downloads" description="Downloads" href="ext:downloads"/>
    <changes label="Change History" description="Change History"
        href="changes.html"/>
    <todo label="Todo" href="todo.html" description="Todo"/>
    <contribute label="How To Contribute" href="contribute.html"
        description="How To Contribute"/>
    <guides label="Guides">
      <install label="Installing / Upgrading"
          description="Installation / Upgrading Instructions"
          href="guides/install.html"/>
      <!--system label="System Guides">
        <install label="Linux: Running eclimd in the background."
            description="Linux: Running eclimd in the background."
            href="guides/system/linux_initd.html"/>
      </system-->
      <java label="Java Guides">
        <java_project label="Java: Creating A Java Project"
            description="Creating a java project."
            href="guides/java/project.html"/>
        <maven_project label="Maven 1.x: Maintaining Java Classpath"
            description="Maintaining java classpath with maven 1.x."
            href="guides/java/maven/maven_classpath.html"/>
        <mvn_project label="Maven 2.x: Maintaining Java Classpath"
            description="Maintaining java classpath with maven 2.x."
            href="guides/java/maven/mvn_classpath.html"/>
        <ivy_project label="Ivy: Maintaining Java Classpath"
            description="Maintaining java classpath with ivy."
            href="guides/java/ivy/ivy_classpath.html"/>
      </java>
      <php label="Php Guides">
        <php_project label="Php: Creating A Php Project"
            description="Creating a php project."
            href="guides/php/project.html"/>
      </php>
      <!--python label="Python Guides">
        <python_project label="Python: Creating A Python Project"
            description="Creating a python project."
            href="guides/python/project.html"/>
      </python-->
    </guides>
    <support label="Support">
      <forums label="Forums" href="ext:forums" description="Discussion Forums"/>
      <tracker label="Bugs / Feature Requests" href="ext:tracker"
          description="Bugs / Feature Requests"/>
    </support>
    <related label="Related Projects">
      <eclipse label="Eclipse" href="ext:eclipse" description="Eclipse IDE"/>
      <vim label="Vim" href="ext:vim" description="Vim Editor"/>
      <vimplugin label="Vimplugin" href="ext:vimplugin"
          description="Eclipse plugin to use vim as the editor in Eclipse."/>
      <viplugin label="viPlugin" href="ext:viplugin"
          description="Eclipse editor plugin with vi/vim like functionality."/>
    </related>
  </about>

  <!--server label="Eclimd Server" tab="documentation">
    <eclimd label="Eclimd" href="eclimd.html" description="Eclimd"/>
  </server-->

  <!--client label="Command Line Client" href="client/" tab="client">
    <index label="Index" href="index.html" description="Index"/>
  </client-->

  <vim label="Documentation" href="vim/" tab="documentation">
    <index label="Index" href="index.html" description="Index"/>
    <project label="Settings" href="settings.html"
        description="Eclim settings."/>
    <external label="Issues / Quirks" href="external_editing.html"
        description="Issues / Quirks"/>
    <completion label="Code Completion" href="code_completion.html"
        description="Code Completion in Vim."/>
    <mappings label="Suggested Vim Mappings" href="mappings.html"
        description="List of suggested Vim mappings."/>
    <cheatsheet label="Cheatsheet" href="cheatsheet.html"
        description="List of all eclim Vim commands."/>
    <cheatsheet_pdf label="Cheatsheet (pdf)" href="cheatsheet.pdf"
        description="List of all eclim Vim commands."/>
    <eclimd label="Eclimd Server" href="../eclimd.html"
        description="Info related to running and monitoring the eclimd server."/>
    <translations label="Translations">
      <traditional_chinese label="Tranditional Chinese">
        <cheatsheet label="Cheatsheet" href="cheatsheet_zh_TW.html"/>
        <cheatsheet_pdf label="Cheatsheet (pdf)" href="cheatsheet_zh_TW.pdf"/>
      </traditional_chinese>
    </translations>
    <common label="Common" href="common/">
      <project label="Projects" href="project.html"
          description="Create projects and view/edit project settings."/>
      <taglist label="TagList Integration" href="taglist.html"
          description="TagList Integration"/>
      <utility label="Utility Commands" href="util.html"
          description="Utility Commands."/>
      <vcs label="Version Control System Commands" href="vcs.html"
          description="Version Control System Commands."/>
      <web label="Web Lookup Commands" href="web.html"
          description="Web Lookup Commands."/>
      <maximize label="Vim Window Maximize / Minimize" href="maximize.html"
          description="Vim Window Maximize / Minimize"/>
    </common>
    <css label="Css" href="css/">
      <complete label="Code Completion" href="complete.html" description="Code Completion"/>
      <validate label="Validation" href="validate.html" description="Validation"/>
    </css>
    <dtd label="Dtd" href="dtd/">
      <complete label="Validation" href="validate.html" description="Validation"/>
    </dtd>
    <html label="Html" href="html/">
      <complete label="Code Completion" href="complete.html" description="Code Completion"/>
      <complete label="Validation" href="validate.html" description="Validation"/>
    </html>
    <java label="Java" href="java/">
      <ant label="Ant" href="ant/">
        <run label="Execution" href="run.html"
            description="Executing Ant"/>
        <complete label="Code Completion" href="complete.html"
            description="Code Completion"/>
        <validate label="Validation" href="validate.html"
            description="Validation"/>
        <doc label="Documentation" href="doc.html"
            description="Ant Documentation Lookup"/>
      </ant>
      <log4j label="Log4j" href="log4j/">
        <validate label="Validation" href="validate.html"
            description="Validation"/>
      </log4j>
      <maven label="Maven" href="maven/">
        <run label="Execution" href="run.html"
            description="Executing Maven"/>
        <dependency label="Dependencies" href="dependency.html"
            description="Maven Dependencies"/>
      </maven>
      <webxml label="WebXml" href="webxml/">
        <validate label="Validation" href="validate.html"
            description="Validation"/>
      </webxml>
      <classpath label="Classpath" href="classpath.html"
          description="Editing your project's classpath"/>
      <source label="Source Code Validation" href="source.html"
          description="Source Code Validation"/>
      <search label="Searching" href="search.html"
          description="Source code searching"/>
      <doc label="Javadocs" href="doc.html"
          description="Javadoc support"/>
      <import label="Imports" href="import.html"
          description="Automated imports"/>
      <complete label="Code Completion" href="complete.html"
          description="Code Completion"/>
      <correct label="Code Correction" href="correct.html"
          description="Code Correction"/>
      <constructor label="Constructor Generation" href="constructor.html"
          description="Constructor generation."/>
      <impl label="Implementation / Override Stubbing" href="impl.html"
          description="Implementation / Override Stubbing"/>
      <delegate label="Delegate Method Creation" href="delegate.html"
          description="Delegate Method Creation"/>
      <bean label="Java Bean Getter / Setter Generation" href="bean.html"
          description="Java Bean Getter / Setter Generation"/>
      <junit label="JUnit Integration" href="junit.html"
          description="JUnit Integration"/>
      <testng label="TestNG Integration" href="testng.html"
          description="TestNG Integration"/>
      <logging label="Logging" href="logging.html"
          description="Logging"/>
      <abbreviations label="Abbreviations" href="abbreviations.html"
          description="Abbreviations"/>
      <regex label="Regex" href="regex.html"
          description="Regular Expression Testing"/>
      <tools label="Tools" href="tools.html"
          description="JDK Tools Integration"/>
    </java>
    <php label="Php" href="php/">
      <includepath label="Include Path" href="includepath.html"
          description="Include Path"/>
      <complete label="Code Completion" href="complete.html"
          description="Code Completion"/>
      <definition label="Search" href="search.html"
          description="Search"/>
    </php>
    <python label="Python" href="python/">
      <!--complete label="Code Completion" href="complete.html"
          description="Code Completion"/>
      <definition label="Jumping To Definition" href="definition.html"
          description="Code Completion"/-->
      <regex label="Regex" href="regex.html"
          description="Regular Expression Testing"/>
      <django label="Django" href="django.html"
          description="Django Support"/>
    </python>
    <vim label="Vim Script" href="vim/">
      <find label="Vim Find" href="find.html"
          description="Find Vim declaration or references of functions and global variables."/>
      <doc label="Vim Doc" href="doc.html"
          description="Open Vim help for a keyword."/>
    </vim>
    <wsdl label="Wsdl" href="wsdl/">
      <complete label="Validation" href="validate.html" description="Validation"/>
    </wsdl>
    <xml label="Xml" href="xml/">
      <complete label="Code Completion" href="complete.html" description="Code Completion"/>
      <definition label="Definition Lookup" href="definition.html"
          description="Definition Lookup"/>
      <validate label="Validation" href="validate.html"
          description="Validation"/>
      <format label="Format" href="format.html" description="Format"/>
    </xml>
    <xsd label="Xsd" href="xsd/">
      <complete label="Validation" href="validate.html" description="Validation"/>
    </xsd>
  </vim>

  <external-refs>
    <downloads href="http://sourceforge.net/project/showfiles.php?group_id=145869"/>
    <screenshots href="http://sourceforge.net/project/screenshots.php?group_id=145869"/>
    <forums href="http://sourceforge.net/forum/?group_id=145869"/>
    <tracker href="http://sourceforge.net/tracker/?group_id=145869"/>
    <license href="http://apache.org/licenses/LICENSE-2.0.html"/>

    <jdk_download href="http://java.sun.com/javase/downloads/index.html"/>

    <eclipse href="http://eclipse.org"/>
    <eclipse_download href="http://eclipse.org/downloads/index.php"/>
    <eclipse_pdt href="http://eclipse.org/pdt/"/>
    <eclipse_wst href="http://eclipse.org/webtools/main.php"/>
    <pydev href="http://pydev.sourceforge.net"/>

    <vim href="http://www.vim.org"/>
    <vim_download href="http://www.vim.org/download.php"/>
    <!--vim_windows href="http://users.skynet.be/antoine.mechelynck/vim/#vim7"/-->
    <nailgun href="http://www.martiansoftware.com/nailgun/"/>

    <supertab href="http://www.vim.org/scripts/script.php?script_id=1643"/>

    <taglist href="http://www.vim.org/scripts/script.php?script_id=273"/>
    <taglist_extend
        href="http://www.geocities.com/yegappan/taglist/manual.html#taglist-extend"/>
    <taglist_ctags
        href="http://www.geocities.com/yegappan/taglist/manual.html#'Tlist_Ctags_Cmd'"/>

    <vimplugin href="http://vimplugin.sourceforge.net/"/>
    <viplugin href="http://www.satokar.com/viplugin/index.php"/>

    <antcontrib href="http://ant-contrib.sourceforge.net"/>

    <groovy href="http://groovy.codehaus.org"/>

    <ant href="http://ant.apache.org"/>
    <maven href="http://maven.apache.org"/>
    <ivy href="http://jayasoft.org/ivy"/>
    <formic href="http://sourceforge.net/projects/formic"/>

    <viewvc href="http://viewvc.org"/>

    <testng href="http://testng.org/doc"/>

    <forrest href="http://forrest.apache.org/"/>
    <cocoon href="http://cocoon.apache.org/"/>
    <xml.apache.org href="http://xml.apache.org/"/>
  </external-refs>

</site>
